mosaik.HDF5_Storage-0.1.0rc20210812000441-py3.8-nspkg.pth
mosaik_hdf5_storage/hdf5_storage/__init__.py
mosaik_hdf5_storage/hdf5_storage/reader.py
mosaik_hdf5_storage/hdf5_storage/writer.py
mosaik_hdf5_storage/hdf5_storage/library/__init__.py
mosaik_hdf5_storage/hdf5_storage/library/ensure_path.py
mosaik_hdf5_storage/hdf5_storage/library/get_hdf5_filepath_module.py
mosaik_hdf5_storage/hdf5_storage/library/get_options_module.py
mosaik_hdf5_storage/hdf5_storage/library/get_path_module.py
mosaik_hdf5_storage/hdf5_storage/mock/__init__.py
mosaik_hdf5_storage/hdf5_storage/mock/mock_meta.py
mosaik_hdf5_storage/hdf5_storage/mock/mock_model.py
mosaik_hdf5_storage/hdf5_storage/mock/mock_simulator.py
mosaik_hdf5_storage/hdf5_storage/util/__init__.py
mosaik_hdf5_storage/hdf5_storage/util/paths.py
mosaik.HDF5_Storage-0.1.0rc20210812000441.dist-info/LICENSE.txt
mosaik.HDF5_Storage-0.1.0rc20210812000441.dist-info/METADATA
mosaik.HDF5_Storage-0.1.0rc20210812000441.dist-info/WHEEL
mosaik.HDF5_Storage-0.1.0rc20210812000441.dist-info/entry_points.txt
mosaik.HDF5_Storage-0.1.0rc20210812000441.dist-info/namespace_packages.txt
mosaik.HDF5_Storage-0.1.0rc20210812000441.dist-info/top_level.txt
mosaik.HDF5_Storage-0.1.0rc20210812000441.dist-info/RECORD
